custardpy/CannyEdge.py
custardpy/Cluster.py
custardpy/DirectionalRelativeFreq.py
custardpy/DirectionalityIndex.py
custardpy/HiCmodule.py
custardpy/InsulationScore.py
custardpy/PlotModule.py
custardpy/__init__.py
custardpy/checkHiCfile.py
custardpy/convert_JuicerDump_to_dense.py
custardpy/generateCmap.py
custardpy/loadData.py
custardpy/plotHiCfeature_module.py
custardpy-0.7.6.data/scripts/DEG_boundary_analysis
custardpy-0.7.6.data/scripts/InsulationScore.py
custardpy-0.7.6.data/scripts/checkHiCfile.py
custardpy-0.7.6.data/scripts/convert_JuicerDump_to_dense.py
custardpy-0.7.6.data/scripts/custardpy_clustering_boundary
custardpy-0.7.6.data/scripts/custardpy_differential_DRF
custardpy-0.7.6.data/scripts/drawSquareMulti
custardpy-0.7.6.data/scripts/drawSquarePair
custardpy-0.7.6.data/scripts/drawSquareRatioMulti
custardpy-0.7.6.data/scripts/drawSquareRatioPair
custardpy-0.7.6.data/scripts/drawTriangleMulti
custardpy-0.7.6.data/scripts/drawTrianglePair
custardpy-0.7.6.data/scripts/getBoundaryfromInsulationScore
custardpy-0.7.6.data/scripts/plotCompartmentGenome
custardpy-0.7.6.data/scripts/plotHiCMatrix
custardpy-0.7.6.data/scripts/plotHiCfeature
custardpy-0.7.6.data/scripts/plotInsulationScore
custardpy-0.7.6.data/scripts/plotMultiScaleInsulationScore
custardpy-0.7.6.dist-info/METADATA
custardpy-0.7.6.dist-info/WHEEL
custardpy-0.7.6.dist-info/top_level.txt
custardpy-0.7.6.dist-info/RECORD
