Metadata-Version: 2.1
Name: custardpy
Version: 0.7.6
Summary: Hi-C analysis tools by Python3
Home-page: https://github.com/rnakato/custardpy
Author: Ryuichiro Nakato
Author-email: rnakato@iqb.u-tokyo.ac.jp
License: GPL3.0
Keywords: Hi-C analysis,3D genome,NGS
Classifier: Programming Language :: Python :: 3
Classifier: Operating System :: OS Independent
Requires-Python: >=3.7
Requires-Dist: numpy >=1.18
Requires-Dist: pandas >=1.3.0
Requires-Dist: scipy >=1.3
Requires-Dist: scikit-learn >=1.0.0
Requires-Dist: matplotlib >=3.2.2
Requires-Dist: seaborn >=0.11.1
Requires-Dist: h1d >=0.2.0
Requires-Dist: hic-straw >=1.3.0
